MANIFEST.in
README.rst
setup.py
Flask_Bootstrap.egg-info/PKG-INFO
Flask_Bootstrap.egg-info/SOURCES.txt
Flask_Bootstrap.egg-info/dependency_links.txt
Flask_Bootstrap.egg-info/not-zip-safe
Flask_Bootstrap.egg-info/requires.txt
Flask_Bootstrap.egg-info/top_level.txt
flask_bootstrap/__init__.py
flask_bootstrap/static/jquery.js
flask_bootstrap/static/jquery.min.js
flask_bootstrap/static/css/bootstrap-theme.css
flask_bootstrap/static/css/bootstrap-theme.css.map
flask_bootstrap/static/css/bootstrap-theme.min.css
flask_bootstrap/static/css/bootstrap.css
flask_bootstrap/static/css/bootstrap.css.map
flask_bootstrap/static/css/bootstrap.min.css
flask_bootstrap/static/fonts/glyphicons-halflings-regular.eot
flask_bootstrap/static/fonts/glyphicons-halflings-regular.svg
flask_bootstrap/static/fonts/glyphicons-halflings-regular.ttf
flask_bootstrap/static/fonts/glyphicons-halflings-regular.woff
flask_bootstrap/static/js/bootstrap.js
flask_bootstrap/static/js/bootstrap.min.js
flask_bootstrap/templates/bootstrap/base.html
flask_bootstrap/templates/bootstrap/fixes.html
flask_bootstrap/templates/bootstrap/google.html
flask_bootstrap/templates/bootstrap/wtf.html