Metadata-Version: 1.1
Name: Flask-Bootstrap
Version: 3.1.0.1
Summary: An extension that includes Twitter's Bootstrap in your project, without any boilerplate code.
Home-page: http://github.com/mbr/flask-bootstrap
Author: Marc Brinkmann
Author-email: git@marcbrinkmann.de
License: BSD
Platform: any
Classifier: Environment :: Web Environment
Classifier: Intended Audience :: Developers
Classifier: License :: OSI Approved :: BSD License
Classifier: Operating System :: OS Independent
Classifier: Programming Language :: Python
Classifier: Topic :: Internet :: WWW/HTTP :: Dynamic Content
Classifier: Topic :: Software Development :: Libraries :: Python Modules
